unalengua/__init__.py
unalengua-0.0.2.dist-info/LICENSE
unalengua-0.0.2.dist-info/METADATA
unalengua-0.0.2.dist-info/WHEEL
unalengua-0.0.2.dist-info/top_level.txt
unalengua-0.0.2.dist-info/RECORD
