Metadata-Version: 2.1
Name: unalengua
Version: 0.0.2
Summary: A simple library for Unalengua API.
Home-page: https://github.com/Jelouh/unalengua
Author: Francisco Griman
Author-email: grihardware@gmail.com
License: MIT
Classifier: Intended Audience :: Developers
Classifier: Programming Language :: Python :: 3
Classifier: Programming Language :: Python :: 3.12
License-File: LICENSE
Requires-Dist: requests >=2.32.3
Requires-Dist: ua-generator ==1.0.5
